wsltools/__init__.py
wsltools/checksec.py
wsltools/datatype.py
wsltools/domaintools.py
wsltools/faker.py
wsltools/similar.py
wsltools/urlclean.py
wsltools/utils/TLDS.py
wsltools/utils/UAS.py
wsltools/utils/WAFS.py
wsltools/utils/__init__.py
wsltools/utils/compat.py
wsltools/utils/domaintools.py
wsltools/utils/ipaddr.py
wsltools/utils/faker/__init__.py
wsltools/utils/faker/config.py
wsltools/utils/faker/factory.py
wsltools/utils/faker/generator.py
wsltools/utils/faker/proxy.py
wsltools/utils/faker/providers/__init__.py
wsltools/utils/faker/providers/address/__init__.py
wsltools/utils/faker/providers/address/cs_CZ/__init__.py
wsltools/utils/faker/providers/address/de/__init__.py
wsltools/utils/faker/providers/address/de_AT/__init__.py
wsltools/utils/faker/providers/address/de_DE/__init__.py
wsltools/utils/faker/providers/address/el_GR/__init__.py
wsltools/utils/faker/providers/address/en/__init__.py
wsltools/utils/faker/providers/address/en_AU/__init__.py
wsltools/utils/faker/providers/address/en_CA/__init__.py
wsltools/utils/faker/providers/address/en_GB/__init__.py
wsltools/utils/faker/providers/address/en_NZ/__init__.py
wsltools/utils/faker/providers/address/en_PH/__init__.py
wsltools/utils/faker/providers/address/en_US/__init__.py
wsltools/utils/faker/providers/address/es/__init__.py
wsltools/utils/faker/providers/address/es_ES/__init__.py
wsltools/utils/faker/providers/address/es_MX/__init__.py
wsltools/utils/faker/providers/address/fa_IR/__init__.py
wsltools/utils/faker/providers/address/fi_FI/__init__.py
wsltools/utils/faker/providers/address/fil_PH/__init__.py
wsltools/utils/faker/providers/address/fr_CH/__init__.py
wsltools/utils/faker/providers/address/fr_FR/__init__.py
wsltools/utils/faker/providers/address/he_IL/__init__.py
wsltools/utils/faker/providers/address/hi_IN/__init__.py
wsltools/utils/faker/providers/address/hr_HR/__init__.py
wsltools/utils/faker/providers/address/hu_HU/__init__.py
wsltools-0.2.4.dist-info/DESCRIPTION.rst
wsltools-0.2.4.dist-info/METADATA
wsltools-0.2.4.dist-info/RECORD
wsltools-0.2.4.dist-info/WHEEL
wsltools-0.2.4.dist-info/metadata.json
wsltools-0.2.4.dist-info/top_level.txt
wsltools-0.2.4.dist-info/zip-safe
