Metadata-Version: 2.0
Name: wsltools
Version: 0.2.4
Summary: Web Scan Lazy Tools
Home-page: https://github.com/symbo1/wsltools
Author: CongRong
Author-email: tr3jer@gmail.com
License: MIT
Project-URL: Source, https://github.com/symbo1/wsltools
Project-URL: Documentation, https://wsltools.readthedocs.io
Keywords: security,security-tools,security-scanner,security-automation,security-audit,spider,spider-framework,scanner-web,security-tool,crawling-framework,web-vulnerability-scanners
Platform: UNKNOWN
Classifier: Development Status :: 5 - Production/Stable
Classifier: Intended Audience :: Developers
Classifier: License :: OSI Approved :: MIT License
Classifier: Programming Language :: Python
Classifier: Programming Language :: Python :: 2
Classifier: Programming Language :: Python :: 2.7
Classifier: Programming Language :: Python :: 3
Classifier: Programming Language :: Python :: 3.5
Classifier: Programming Language :: Python :: 3.6
Classifier: Programming Language :: Python :: 3.7
Classifier: Programming Language :: Python :: 3.8
Classifier: Programming Language :: Python :: Implementation :: CPython
Classifier: Programming Language :: Python :: Implementation :: PyPy
Requires-Python: >=2.7, !=3.0.*, !=3.1.*, !=3.2.*, !=3.3.*, !=3.4.*
